main/__init__.py
main/main.py
main/lib/Argument.py
main/lib/Command_help.py
main/lib/Help.py
main/lib/Validation_command.py
main/lib/Validation_funtion.py
main/lib/__init__.py
Medical_media_sridhar-0.1.3.dist-info/METADATA
Medical_media_sridhar-0.1.3.dist-info/WHEEL
Medical_media_sridhar-0.1.3.dist-info/entry_points.txt
Medical_media_sridhar-0.1.3.dist-info/top_level.txt
Medical_media_sridhar-0.1.3.dist-info/RECORD
