Metadata-Version: 2.1
Name: Medical-media-sridhar
Version: 0.1.3
Summary: Medical_media gives the status of our Health Condition
Home-page: https://git.selfmade.ninja/SRIDHARDSCV/bmi_calculater_python_project
Author: Sridhar
Author-email: dcsvsridhar@gmail.com
License: UNKNOWN
Platform: UNKNOWN
